gpm_player/__init__.py
gpm_player/__version__.py
gpm_player/common.py
gpm_player/exceptions.py
gpm_player/playlist.py
gpm_player/station.py
gpm_player-0.1.2.dist-info/DESCRIPTION.rst
gpm_player-0.1.2.dist-info/METADATA
gpm_player-0.1.2.dist-info/RECORD
gpm_player-0.1.2.dist-info/WHEEL
gpm_player-0.1.2.dist-info/entry_points.txt
gpm_player-0.1.2.dist-info/metadata.json
gpm_player-0.1.2.dist-info/top_level.txt
