Metadata-Version: 2.0
Name: gpm-player
Version: 0.1.2
Summary: Multi platform and text based Google-Play-Music player
Home-page: http://github.com/johejo/gpm-player
Author: Mitsuo Heijo
Author-email: mitsuo_h@outlook.com
License: MIT
Platform: UNKNOWN
Classifier: Environment :: Console
Classifier: License :: OSI Approved :: MIT License
Classifier: Operating System :: MacOS :: MacOS X
Classifier: Operating System :: Microsoft :: Windows
Classifier: Operating System :: POSIX :: Linux
Classifier: Programming Language :: Python :: 3 :: Only
Classifier: Programming Language :: Python :: 3.6
Classifier: Topic :: Multimedia :: Sound/Audio :: Players
Classifier: Topic :: Terminals
Requires-Python: >=3.5
Requires-Dist: gmusicapi (>=11.0.0)
Requires-Dist: inputimeout (>=1.0.4)
Requires-Dist: python-vlc (>=3.0.102)
